readmecraft/BLANK_README.md
readmecraft/__init__.py
readmecraft/config.py
readmecraft/core.py
readmecraft/utils/__init__.py
readmecraft/utils/cli.py
readmecraft/utils/file_handler.py
readmecraft/utils/image_converter.py
readmecraft/utils/llm.py
readmecraft/utils/logo_generator.py
readmecraft-0.1.8.dist-info/METADATA
readmecraft-0.1.8.dist-info/WHEEL
readmecraft-0.1.8.dist-info/entry_points.txt
readmecraft-0.1.8.dist-info/top_level.txt
readmecraft-0.1.8.dist-info/RECORD
