Metadata-Version: 2.4
Name: readmecraft
Version: 0.1.8
Summary: A tool to automatically generate README files for your projects.
Author-email: stone91 <m370025263@gmail.com>, lintao <lint22@mails.tsinghua.edu.cn>
Project-URL: Homepage, https://github.com/lintaojlu/auto_readme
Project-URL: Bug Tracker, https://github.com/lintaojlu/auto_readme/issues
Classifier: Programming Language :: Python :: 3
Classifier: License :: OSI Approved :: MIT License
Classifier: Operating System :: OS Independent
Requires-Python: >=3.8
Requires-Dist: openai>=1.0.0
Requires-Dist: requests
Requires-Dist: rich
Requires-Dist: drawsvg
Requires-Dist: cairosvg
